msr/__init__.py
msr_by_sooz-1.0.0.data/scripts/msr.py
msr_by_sooz-1.0.0.dist-info/LICENSE
msr_by_sooz-1.0.0.dist-info/METADATA
msr_by_sooz-1.0.0.dist-info/WHEEL
msr_by_sooz-1.0.0.dist-info/top_level.txt
msr_by_sooz-1.0.0.dist-info/RECORD
