Metadata-Version: 2.1
Name: msr-by-sooz
Version: 1.0.0
Summary: a CLI for measuring things on web pages!
Home-page: https://github.com/pypa/sampleproject
Author: sooz
Author-email: smeyer101@mac.com
License: UNKNOWN
Platform: UNKNOWN
Classifier: Programming Language :: Python :: 3
Classifier: License :: OSI Approved :: MIT License
Classifier: Operating System :: OS Independent
Requires-Python: >=3.6
Requires-Dist: argparse
Requires-Dist: validator-collection
Requires-Dist: requests
Requires-Dist: texttable
Requires-Dist: tldextract
Requires-Dist: tabulate
